examples/__init__.py
examples/rss_rum_to_xin/__init__.py
examples/rss_rum_to_xin/bot.py
examples/rss_rum_to_xin/config_rss.py
examples/rss_rum_to_xin/do_airdrop.py
examples/rss_rum_to_xin/do_count_users.py
examples/rss_rum_to_xin/do_rss_blaze.py
examples/rss_rum_to_xin/modules.py
examples/rss_rum_to_xin/seven_years_circle.py
old_tests_temp/__init__.py
old_tests_temp/check_profile_imgs_size.py
old_tests_temp/temp_test_db.py
old_tests_temp/temp_test_epub.py
old_tests_temp/temp_test_poa_eth.py
old_tests_temp/test_baseapi.py
old_tests_temp/test_chain.py
old_tests_temp/test_chainconfig.py
old_tests_temp/test_configs.py
old_tests_temp/test_content.py
old_tests_temp/test_flask_full.py
old_tests_temp/test_flask_light.py
old_tests_temp/test_full_profile.py
old_tests_temp/test_full_send_trxs.py
old_tests_temp/test_light_node.py
old_tests_temp/test_light_profile_update.py
old_tests_temp/test_light_send_trxs.py
old_tests_temp/test_mix_nodes.py
old_tests_temp/test_network.py
old_tests_temp/test_paidgroup.py
old_tests_temp/test_pubqueue.py
rumpy/__init__.py
rumpy/exceptions.py
rumpy/utils.py
rumpy/api/__init__.py
rumpy/api/base.py
rumpy/api/full_node.py
rumpy/api/light_node.py
rumpy/api/paidgroup.py
rumpy/api/rum_poa.py
rumpy/bots/__init__.py
rumpy/bots/export_data.py
rumpy/bots/group_statistics.py
rumpy/bots/search_seeds.py
rumpy/bots/search_user.py
rumpy/client/__init__.py
rumpy/client/_flask_extensions.py
rumpy/client/_requests.py
rumpy/client/full_node_client.py
rumpy/client/light_node_client.py
rumpy/types/__init__.py
rumpy/types/data.py
rumpy/types/pack_trx.py
rumpy-0.9.2.dist-info/LICENSE
rumpy-0.9.2.dist-info/METADATA
rumpy-0.9.2.dist-info/WHEEL
rumpy-0.9.2.dist-info/top_level.txt
rumpy-0.9.2.dist-info/RECORD
