Metadata-Version: 2.1
Name: rumpy
Version: 0.9.2
Summary: python sdk for quorum: https://github.com/rumsystem/quorum
Home-page: https://github.com/liujuanjuan1984/rumpy
Author: liujuanjuan1984
Author-email: qiaoanlu@163.com
Project-URL: Github Repo, https://github.com/liujuanjuan1984/rumpy
Project-URL: Bug Tracker, https://github.com/liujuanjuan1984/rumpy/issues
Project-URL: About Quorum, https://github.com/rumsystem/quorum
Keywords: rumpy,rumsystem,quorum
Classifier: Programming Language :: Python :: 3
Classifier: Programming Language :: Python :: 3.8
Classifier: License :: OSI Approved :: GNU General Public License v3 (GPLv3)
Classifier: Operating System :: OS Independent
Requires-Python: >=3.8
License-File: LICENSE
Requires-Dist: requests
Requires-Dist: filetype
Requires-Dist: pillow
